py_postgresql_wrapper/__init__.py
py_postgresql_wrapper/configuration.py
py_postgresql_wrapper/database.py
tests/__init__.py
tests/test.py
py_postgresql_wrapper-1.0.4.dist-info/LICENSE
py_postgresql_wrapper-1.0.4.dist-info/METADATA
py_postgresql_wrapper-1.0.4.dist-info/WHEEL
py_postgresql_wrapper-1.0.4.dist-info/top_level.txt
py_postgresql_wrapper-1.0.4.dist-info/RECORD
