Metadata-Version: 2.1
Name: py-postgresql-wrapper
Version: 1.0.4
Summary: PyPostgreSQLWrapper is a simple adapter for PostgreSQL with connection pooling
Home-page: https://github.com/bernardocouto/py-postgresql-wrapper
Author: Bernardo Couto
Author-email: bernardocouto.py@gmail.com
License: GPLv3
Keywords: database postgresql psycopg2 queries
Platform: UNKNOWN
Classifier: License :: OSI Approved :: GNU General Public License v3 (GPLv3)
Classifier: Operating System :: OS Independent
Classifier: Programming Language :: Python
Classifier: Topic :: Database
Requires-Dist: dbutils
Requires-Dist: psycopg2-binary
